{
    "country": "Saint Lucia",
    "country_code": "LC",
    "list": [
        {
            "id": "1",
            "bank": "1ST NATIONAL BANK ST.LUCIA LIMITED",
            "city": "CASTRIES",
            "branch": null,
            "swift_code": "LUOBLCLC"
        },
        {
            "id": "2",
            "bank": "BANK OF NOVA SCOTIA,THE",
            "city": "CASTRIES",
            "branch": null,
            "swift_code": "NOSCLCLC"
        },
        {
            "id": "3",
            "bank": "BANK OF SAINT LUCIA INTERNATIONAL LIMITED",
            "city": "GROS-ISLET",
            "branch": null,
            "swift_code": "BSLULCLC"
        },
        {
            "id": "4",
            "bank": "BANK OF SAINT LUCIA LIMITED",
            "city": "CASTRIES",
            "branch": null,
            "swift_code": "BOSLLCLC"
        },
        {
            "id": "5",
            "bank": "FIRSTCARIBBEAN INTERNATIONAL BANK",
            "city": "CASTRIES",
            "branch": null,
            "swift_code": "FCIBLCLC"
        },
        {
            "id": "6",
            "bank": "GOVERNMENT OF SAINT LUCIA",
            "city": "CASTRIES",
            "branch": null,
            "swift_code": "GVLCLCLC"
        },
        {
            "id": "7",
            "bank": "HERMES BANK LIMITED",
            "city": "GROS-ISLET",
            "branch": null,
            "swift_code": "HEMMLCL2"
        },
        {
            "id": "8",
            "bank": "PETRUS PRIVATE BANK",
            "city": "CASTRIES",
            "branch": null,
            "swift_code": "PTRVLCLC"
        },
        {
            "id": "9",
            "bank": "PLG CAPITAL BANK LTD",
            "city": "CASTRIES",
            "branch": null,
            "swift_code": "PLGCLCLC"
        },
        {
            "id": "10",
            "bank": "ROYAL BANK OF CANADA",
            "city": "CASTRIES",
            "branch": null,
            "swift_code": "ROYCLCLC"
        },
        {
            "id": "11",
            "bank": "STATETRUST BANK AND TRUST LTD.",
            "city": "CASTRIES",
            "branch": null,
            "swift_code": "STTTLCLC"
        }
    ]
}
